visapy/__init__.py
visapy/example.py
visapy-0.0.1.dist-info/METADATA
visapy-0.0.1.dist-info/WHEEL
visapy-0.0.1.dist-info/licenses/LICENSE
visapy-0.0.1.dist-info/RECORD
